securepasswordgenerator/__init__.py
securepasswordgenerator/securepasswordgenerator.py
securepasswordgenerator-2.0.0.dist-info/LICENSE
securepasswordgenerator-2.0.0.dist-info/METADATA
securepasswordgenerator-2.0.0.dist-info/WHEEL
securepasswordgenerator-2.0.0.dist-info/entry_points.txt
securepasswordgenerator-2.0.0.dist-info/top_level.txt
securepasswordgenerator-2.0.0.dist-info/RECORD
