Metadata-Version: 2.1
Name: securepasswordgenerator
Version: 2.0.0
Summary: SecurePasswordGenerator is a tool for generating random passwords. It provides both command line utility and underlying python module.
Home-page: https://github.com/quillfires/SecurePasswordGenerator
Author: Ali Fayaz (Quill)
Author-email: fayaz.quill@gmail.com
License: MIT
Keywords: password generator
Classifier: Programming Language :: Python
Classifier: Programming Language :: Python :: 2
Classifier: Programming Language :: Python :: 2.6
Classifier: Programming Language :: Python :: 2.7
Classifier: Programming Language :: Python :: 3
Classifier: Programming Language :: Python :: 3.4
Classifier: Programming Language :: Python :: 3.5
Classifier: Programming Language :: Python :: 3.6
Classifier: Programming Language :: Python :: 3.7
Classifier: Programming Language :: Python :: 3.8
Classifier: Programming Language :: Python :: 3.9
Classifier: Programming Language :: Python :: 3.10
Classifier: Programming Language :: Python :: 3.11
Classifier: Topic :: Utilities
Classifier: License :: OSI Approved :: MIT License
Classifier: Development Status :: 5 - Production/Stable
License-File: LICENSE
